{
  "$schema": "https://developer.microsoft.com/json-schemas/fabric/item/report/definition/visualContainer/2.9.0/schema.json",
  "name": "99646ecfcd6ca802a1d3",
  "position": {
    "x": 1027.6847290640394,
    "y": 8.8669950738916263,
    "z": 20000,
    "height": 80.6896551724138,
    "width": 242.95566502463055,
    "tabOrder": 20000
  },
  "visual": {
    "visualType": "slicer",
    "query": {
      "queryState": {
        "Values": {
          "projections": [
            {
              "field": {
                "Column": {
                  "Expression": {
                    "SourceRef": {
                      "Entity": "dim_detalhes"
                    }
                  },
                  "Property": "Complexidade do Procedimento"
                }
              },
              "queryRef": "dim_detalhes.Complexidade do Procedimento",
              "nativeQueryRef": "Complexidade do Procedimento",
              "active": true
            }
          ]
        }
      }
    },
    "objects": {
      "data": [
        {
          "properties": {
            "mode": {
              "expr": {
                "Literal": {
                  "Value": "'Basic'"
                }
              }
            }
          }
        }
      ],
      "general": [
        {
          "properties": {
            "orientation": {
              "expr": {
                "Literal": {
                  "Value": "1D"
                }
              }
            },
            "outlineColor": {
              "solid": {
                "color": {
                  "expr": {
                    "ThemeDataColor": {
                      "ColorId": 0,
                      "Percent": -0.2
                    }
                  }
                }
              }
            }
          }
        }
      ],
      "header": [
        {
          "properties": {
            "show": {
              "expr": {
                "Literal": {
                  "Value": "false"
                }
              }
            }
          }
        }
      ],
      "slider": [
        {
          "properties": {
            "show": {
              "expr": {
                "Literal": {
                  "Value": "false"
                }
              }
            }
          }
        }
      ],
      "selection": [
        {
          "properties": {
            "selectAllCheckboxEnabled": {
              "expr": {
                "Literal": {
                  "Value": "false"
                }
              }
            },
            "singleSelect": {
              "expr": {
                "Literal": {
                  "Value": "true"
                }
              }
            },
            "strictSingleSelect": {
              "expr": {
                "Literal": {
                  "Value": "false"
                }
              }
            }
          }
        }
      ],
      "items": [
        {
          "properties": {
            "outlineStyle": {
              "expr": {
                "Literal": {
                  "Value": "15D"
                }
              }
            },
            "padding": {
              "expr": {
                "Literal": {
                  "Value": "0D"
                }
              }
            }
          }
        }
      ]
    },
    "visualContainerObjects": {
      "title": [
        {
          "properties": {
            "show": {
              "expr": {
                "Literal": {
                  "Value": "true"
                }
              }
            },
            "text": {
              "expr": {
                "Literal": {
                  "Value": "'Complexidade'"
                }
              }
            },
            "fontSize": {
              "expr": {
                "Literal": {
                  "Value": "9D"
                }
              }
            },
            "alignment": {
              "expr": {
                "Literal": {
                  "Value": "'center'"
                }
              }
            }
          }
        }
      ],
      "background": [
        {
          "properties": {
            "show": {
              "expr": {
                "Literal": {
                  "Value": "false"
                }
              }
            }
          }
        }
      ],
      "border": [
        {
          "properties": {
            "show": {
              "expr": {
                "Literal": {
                  "Value": "false"
                }
              }
            }
          }
        }
      ],
      "spacing": [
        {
          "properties": {
            "verticalSpacing": {
              "expr": {
                "Literal": {
                  "Value": "0D"
                }
              }
            }
          }
        }
      ],
      "padding": [
        {
          "properties": {
            "bottom": {
              "expr": {
                "Literal": {
                  "Value": "15D"
                }
              }
            },
            "top": {
              "expr": {
                "Literal": {
                  "Value": "0D"
                }
              }
            },
            "right": {
              "expr": {
                "Literal": {
                  "Value": "0D"
                }
              }
            },
            "left": {
              "expr": {
                "Literal": {
                  "Value": "0D"
                }
              }
            }
          }
        }
      ],
      "visualHeader": [
        {
          "properties": {
            "show": {
              "expr": {
                "Literal": {
                  "Value": "false"
                }
              }
            }
          }
        }
      ]
    },
    "drillFilterOtherVisuals": true
  }
}